odoo/addons/pos_product_display_default_code/README.rst
odoo/addons/pos_product_display_default_code/__init__.py
odoo/addons/pos_product_display_default_code/__manifest__.py
odoo/addons/pos_product_display_default_code/i18n/de.po
odoo/addons/pos_product_display_default_code/i18n/es.po
odoo/addons/pos_product_display_default_code/i18n/it.po
odoo/addons/pos_product_display_default_code/i18n/pos_product_display_default_code.pot
odoo/addons/pos_product_display_default_code/models/__init__.py
odoo/addons/pos_product_display_default_code/models/pos_config.py
odoo/addons/pos_product_display_default_code/models/pos_session.py
odoo/addons/pos_product_display_default_code/models/res_config_settings.py
odoo/addons/pos_product_display_default_code/readme/CONFIGURE.rst
odoo/addons/pos_product_display_default_code/readme/CONTRIBUTORS.rst
odoo/addons/pos_product_display_default_code/readme/DESCRIPTION.rst
odoo/addons/pos_product_display_default_code/static/description/config.png
odoo/addons/pos_product_display_default_code/static/description/icon.png
odoo/addons/pos_product_display_default_code/static/description/index.html
odoo/addons/pos_product_display_default_code/tests/__init__.py
odoo/addons/pos_product_display_default_code/tests/test_load_params_product.py
odoo/addons/pos_product_display_default_code/views/res_config_settings_views.xml
odoo_addon_pos_product_display_default_code-16.0.1.0.1.2.dist-info/METADATA
odoo_addon_pos_product_display_default_code-16.0.1.0.1.2.dist-info/WHEEL
odoo_addon_pos_product_display_default_code-16.0.1.0.1.2.dist-info/top_level.txt
odoo_addon_pos_product_display_default_code-16.0.1.0.1.2.dist-info/RECORD
