Metadata-Version: 2.1
Name: odoo-addon-pos_product_display_default_code
Version: 16.0.1.0.1.2
Summary: pos: display product default code before product name
Home-page: https://github.com/OCA/pos
Author: Odoo Community Association (OCA), Akretion, FactorLibre
Author-email: support@odoo-community.org
License: AGPL-3
Classifier: Programming Language :: Python
Classifier: Framework :: Odoo
Classifier: Framework :: Odoo :: 16.0
Classifier: License :: OSI Approved :: GNU Affero General Public License v3
Requires-Python: >=3.10
Requires-Dist: odoo<16.1dev,>=16.0a
